gat_llm/__init__.py
gat_llm/connector_mcp.py
gat_llm/llm_interface.py
gat_llm/llm_invoker.py
gat_llm/llm_providers/__init__.py
gat_llm/llm_providers/anthropic.py
gat_llm/llm_providers/aws_bedrock.py
gat_llm/llm_providers/aws_bedrock_cohere.py
gat_llm/llm_providers/aws_bedrock_nova.py
gat_llm/llm_providers/aws_bedrock_via_openai.py
gat_llm/llm_providers/base_service.py
gat_llm/llm_providers/deepseek.py
gat_llm/llm_providers/grok.py
gat_llm/llm_providers/maritaca.py
gat_llm/llm_providers/ollama.py
gat_llm/llm_providers/openai.py
gat_llm/llm_providers/vllm.py
gat_llm/prompts/__init__.py
gat_llm/prompts/prompt_GAT.txt
gat_llm/prompts/prompt_base.txt
gat_llm/prompts/prompt_generator.py
gat_llm/prompts/.ipynb_checkpoints/prompt_base-checkpoint.txt
gat_llm/tools/__init__.py
gat_llm/tools/base.py
gat_llm/tools/do_date_math.py
gat_llm/tools/get_webpage_contents.py
gat_llm/tools/image_analyzer.py
gat_llm/tools/image_edit.py
gat_llm/tools/make_custom_plot.py
gat_llm/tools/make_qr_code.py
gat_llm/tools/plot_with_graphviz.py
gat_llm/tools/query_database.py
gat_llm/tools/query_database_sales_data_sample.csv
gat_llm/tools/read_file_names_in_local_folder.py
gat_llm/tools/read_local_file.py
gat_llm/tools/run_with_python.py
gat_llm/tools/select_video_frames.py
gat_llm/tools/solve_numeric.py
gat_llm/tools/solve_python_code.py
gat_llm/tools/solve_symbolic.py
gat_llm/tools/speech_to_text.py
gat_llm/tools/speech_transcribe_analyze.py
gat_llm/tools/summarize_past.py
gat_llm/tools/text_to_image.py
gat_llm/tools/text_to_speech.py
gat_llm/tools/update_user_details.py
gat_llm/tools/use_ffmpeg.py
gat_llm/tools/write_local_file.py
gat_llm-0.1.22.dist-info/METADATA
gat_llm-0.1.22.dist-info/WHEEL
gat_llm-0.1.22.dist-info/top_level.txt
gat_llm-0.1.22.dist-info/RECORD
