Metadata-Version: 2.4
Name: gat_llm
Version: 0.1.22
Summary: Generation Augmented by Tools in LLMs - Agentic AI
Author: DCA
License: MIT License
Project-URL: Homepage, https://github.com/douglas125/SelfTestingGAT_LLM
Keywords: large language models,LLMs,RAG,tool use,AI agents
Classifier: License :: OSI Approved :: MIT License
Classifier: Programming Language :: Python
Classifier: Programming Language :: Python :: 3
Requires-Python: >=3.9
Requires-Dist: boto3
Requires-Dist: tqdm
Requires-Dist: graphviz
Requires-Dist: pydot
Requires-Dist: sympy
Requires-Dist: ffmpeg
Requires-Dist: qrcode
Requires-Dist: matplotlib
Requires-Dist: pillow
Requires-Dist: requests
Requires-Dist: beautifulsoup4
Requires-Dist: pandas
Requires-Dist: lxml
Requires-Dist: markitdown
Requires-Dist: pypdf
Requires-Dist: pdf2image
Requires-Dist: duckdb
Requires-Dist: openai
Requires-Dist: anthropic
Provides-Extra: dev
Requires-Dist: black; extra == "dev"
Requires-Dist: pytest; extra == "dev"
Requires-Dist: pytest-timeout; extra == "dev"
Requires-Dist: pre-commit; extra == "dev"
Requires-Dist: coverage; extra == "dev"
